odoo/addons/pos_ticket_extra_company_info_l10n_fr/README.rst
odoo/addons/pos_ticket_extra_company_info_l10n_fr/__init__.py
odoo/addons/pos_ticket_extra_company_info_l10n_fr/__manifest__.py
odoo/addons/pos_ticket_extra_company_info_l10n_fr/i18n/fr.po
odoo/addons/pos_ticket_extra_company_info_l10n_fr/i18n/pos_ticket_extra_company_info_l10n_fr.pot
odoo/addons/pos_ticket_extra_company_info_l10n_fr/readme/CONTRIBUTORS.rst
odoo/addons/pos_ticket_extra_company_info_l10n_fr/readme/CREDITS.rst
odoo/addons/pos_ticket_extra_company_info_l10n_fr/readme/DESCRIPTION.rst
odoo/addons/pos_ticket_extra_company_info_l10n_fr/static/description/icon.png
odoo/addons/pos_ticket_extra_company_info_l10n_fr/static/description/index.html
odoo/addons/pos_ticket_extra_company_info_l10n_fr/static/src/js/db.js
odoo/addons/pos_ticket_extra_company_info_l10n_fr/static/src/xml/pos_ticket_extra_company_info_l10n_fr.xml
odoo/addons/pos_ticket_extra_company_info_l10n_fr/views/templates.xml
odoo12_addon_pos_ticket_extra_company_info_l10n_fr-12.0.1.0.2.dist-info/METADATA
odoo12_addon_pos_ticket_extra_company_info_l10n_fr-12.0.1.0.2.dist-info/WHEEL
odoo12_addon_pos_ticket_extra_company_info_l10n_fr-12.0.1.0.2.dist-info/top_level.txt
odoo12_addon_pos_ticket_extra_company_info_l10n_fr-12.0.1.0.2.dist-info/RECORD
